circle_chain/__init__.py
circle_chain/block.py
circle_chain/common.py
circle_chain/config.yml
circle_chain/node.py
circle_chain/user.py
circle_chain/wallet.py
circle_chain-0.0.4.dist-info/LICENSE
circle_chain-0.0.4.dist-info/METADATA
circle_chain-0.0.4.dist-info/WHEEL
circle_chain-0.0.4.dist-info/top_level.txt
circle_chain-0.0.4.dist-info/RECORD
