Metadata-Version: 2.1
Name: circle_chain
Version: 0.0.4
Summary: circle chain sdk in python
Author-email: lidh04 <lidh04@gmail.com>
License: BSD-3-Clause
Project-URL: Homepage, https://gitee.com/lidh04/python-circle-chain
Project-URL: Issues, https://gitee.com/lidh04/python-circle-chain/issues
Keywords: circle chain,block,wallet,bitcoin
Classifier: Programming Language :: Python :: 3
Classifier: License :: OSI Approved :: MIT License
Classifier: Operating System :: OS Independent
Requires-Python: >=3.8
License-File: LICENSE
Requires-Dist: requests
Requires-Dist: PyYAML
